evalne_gui/__init__.py
evalne_gui/__main__.py
evalne_gui/app.py
evalne_gui/dashboard.py
evalne_gui/index.py
evalne_gui/init_values.py
evalne_gui/monitoring.py
evalne_gui/procinfo.py
evalne_gui/results.py
evalne_gui/settings.py
evalne_gui/utils.py
evalne_gui/assets/main.css
evalne_gui/assets/modal.css
evalne_gui/assets/tabs.css
evalne_gui/assets/icons/dashboard.png
evalne_gui/assets/icons/monitoring.svg
evalne_gui/assets/icons/results.png
evalne_gui/assets/icons/runs.svg
evalne_gui/assets/icons/settings.png
evalne_gui-0.1.0.dist-info/LICENSE
evalne_gui-0.1.0.dist-info/METADATA
evalne_gui-0.1.0.dist-info/WHEEL
evalne_gui-0.1.0.dist-info/entry_points.txt
evalne_gui-0.1.0.dist-info/top_level.txt
evalne_gui-0.1.0.dist-info/RECORD
