Metadata-Version: 2.1
Name: evalne-gui
Version: 0.1.0
Summary: Plotly Dash based GUI for EvalNE
Home-page: https://github.com/Dru-Mara/EvalNE-GUI
Author: Alexandru Mara
Author-email: alexandru.mara@ugent.be
License: MIT License
Keywords: dashboard visualization evaluation monitoring evalne
Classifier: Intended Audience :: Science/Research
Classifier: Intended Audience :: Developers
Classifier: Topic :: Scientific/Engineering :: Information Analysis
Classifier: Topic :: Software Development
Classifier: Programming Language :: Python :: 3
Classifier: License :: OSI Approved :: MIT License
Classifier: Natural Language :: English
Classifier: Operating System :: OS Independent
Requires-Python: >3.6
License-File: LICENSE
Requires-Dist: numpy
Requires-Dist: plotly
Requires-Dist: dash-daq
Requires-Dist: dash-bootstrap-components
Requires-Dist: dash
Requires-Dist: fa2
Requires-Dist: psutil
